pubmed_screen/__init__.py
pubmed_screen/esearch.py
pubmed_screen/main.py
pubmed_screen-0.1.0.dist-info/METADATA
pubmed_screen-0.1.0.dist-info/WHEEL
pubmed_screen-0.1.0.dist-info/entry_points.txt
pubmed_screen-0.1.0.dist-info/licenses/LICENSE
pubmed_screen-0.1.0.dist-info/RECORD
