Metadata-Version: 2.1
Name: pubmed-screen
Version: 0.1.0
Summary: Automates the initial screening phase of systematic PubMed search using keywords.
Author-email: Rami Hamati <rhamati95@gmail.com>
License:                     GNU GENERAL PUBLIC LICENSE
License-File: LICENSE
Keywords: PubMed,citations
Classifier: Development Status :: 4 - Beta
Classifier: Environment :: Console
Classifier: Intended Audience :: Science/Research
Classifier: License :: OSI Approved :: GNU General Public License v3 (GPLv3)
Classifier: Programming Language :: Python :: 3
Requires-Python: >=3.8
Requires-Dist: pandas>=1.5.0
Requires-Dist: requests>=2.28.0
Requires-Dist: seaborn>=0.12.0
Provides-Extra: dev
Requires-Dist: black; extra == 'dev'
